README.rst
setup.py
importceptor/__init__.py
importceptor/importceptor.py
importceptor.egg-info/PKG-INFO
importceptor.egg-info/SOURCES.txt
importceptor.egg-info/dependency_links.txt
importceptor.egg-info/not-zip-safe
importceptor.egg-info/top_level.txt