Metadata-Version: 1.1
Name: importceptor
Version: 0.1.0
Summary: Tool to replace modules on import. Useful for testing code that was not written with testability in mind
Home-page: https://github.com/bgusach/importceptor
Author: Bor González-Usach
Author-email: bgusach@gmail.com
License: BSD
Keywords: importceptor
Platform: UNKNOWN
Classifier: Development Status :: 2 - Pre-Alpha
Classifier: Intended Audience :: Developers
Classifier: License :: OSI Approved :: BSD License
Classifier: Natural Language :: English
Classifier: Programming Language :: Python :: 2
Classifier: Programming Language :: Python :: 2.6
Classifier: Programming Language :: Python :: 2.7
Classifier: Programming Language :: Python :: 3
Classifier: Programming Language :: Python :: 3.3
Classifier: Programming Language :: Python :: 3.4
